MANIFEST.in
README.txt
setup.py
XStatic_jquery_colourpicker.egg-info/PKG-INFO
XStatic_jquery_colourpicker.egg-info/SOURCES.txt
XStatic_jquery_colourpicker.egg-info/dependency_links.txt
XStatic_jquery_colourpicker.egg-info/namespace_packages.txt
XStatic_jquery_colourpicker.egg-info/not-zip-safe
XStatic_jquery_colourpicker.egg-info/top_level.txt
xstatic/__init__.py
xstatic/pkg/__init__.py
xstatic/pkg/jquery_colourpicker/__init__.py
xstatic/pkg/jquery_colourpicker/__init__.pyc
xstatic/pkg/jquery_colourpicker/data/jquery.colourpicker.js