Metadata-Version: 1.0
Name: XStatic-jquery-colourpicker
Version: 1.0.0.1
Summary: jquery-colourpicker 1.0.0 (XStatic packaging standard)
Home-page: http://andreaslagerkvist.com/jquery/colour-picker/
Author: Serghei Mihai
Author-email: smihai@entrouvert.com
License: (same as jquery-colourpicker)
Keywords: jquery_colourpicker xstatic
Platform: any
